h5parm/__init__.py
h5parm/datapack.py
h5parm/maintenance.py
h5parm/utils.py
h5parm/arrays/__init__.py
h5parm/arrays/dsa2000.W.cfg
h5parm/arrays/gmrtPos.cfg
h5parm/arrays/lofar.antenna.cfg
h5parm/arrays/lofar.hba.antenna.cfg
h5parm-1.0.7.dist-info/LICENSE
h5parm-1.0.7.dist-info/METADATA
h5parm-1.0.7.dist-info/WHEEL
h5parm-1.0.7.dist-info/top_level.txt
h5parm-1.0.7.dist-info/RECORD
