Metadata-Version: 2.1
Name: h5parm
Version: 1.0.7
Summary: H5Parm data pack interface
Home-page: https://github.com/joshuaalbert/h5parm
Author: Joshua G. Albert
Author-email: albert@strw.leidenuniv.nl
Classifier: Programming Language :: Python :: 3
Classifier: License :: OSI Approved :: Apache Software License
Classifier: Operating System :: OS Independent
Requires-Python: >=3.6
License-File: LICENSE
